{"_type":"export","__export_format":4,"__export_date":"2024-10-05T03:12:24.411Z","__export_source":"insomnia.desktop.app:v2021.5.0","resources":[{"_id":"wrk_scratchpad","parentId":"proj_scratchpad","modified":1728055535493,"created":1728055535493,"name":"Scratch Pad","description":"","scope":"collection","_type":"workspace"},{"_id":"req_ddaa536fda144bd9aa096975a825e7f8","parentId":"fld_159e7a7b20a04c37a3b5143bba516c5e","modified":1728097914480,"created":1728055641344,"url":"http://127.0.0.1:8000/api/user/create","name":"Create","description":"","method":"POST","body":{"mimeType":"application/json","text":"{\n\t\"first_name\": \"{% faker 'randomFirstName' %}\",\n\t\"last_name\": \"{% faker 'randomLastName' %}\",\n\t\"phone_number\": \"{% faker 'randomPhoneNumber' %}\"\n}"},"parameters":[],"headers":[{"name":"Content-Type","value":"application/json","id":"pair_cb358fd5be044c25826e84a66188463f"},{"name":"User-Agent","value":"insomnia/10.0.0","id":"pair_5fd06ab4dc194df6a9f28f2ce4319d4a"},{"id":"pair_d81e9f4208ee4e1faba51b161fdcbce6","name":"Accept","value":"application/json","description":"","disabled":false,"type":"text","multiline":false}],"authentication":{},"metaSortKey":-1728079703248,"isPrivate":false,"pathParameters":[],"settingStoreCookies":true,"settingSendCookies":true,"settingDisableRenderRequestBody":false,"settingEncodeUrl":true,"settingRebuildPath":true,"settingFollowRedirects":"global","_type":"request"},{"_id":"req_036490ce3b0945f68f013f0f7eda84df","parentId":"fld_159e7a7b20a04c37a3b5143bba516c5e","modified":1728079725563,"created":1728077308579,"url":"http://127.0.0.1:8000/api/users","name":"GetAll","description":"","method":"GET","body":{},"parameters":[],"headers":[{"name":"User-Agent","value":"insomnia/10.0.0"}],"authentication":{},"metaSortKey":-1728079703323,"isPrivate":false,"pathParameters":[],"settingStoreCookies":true,"settingSendCookies":true,"settingDisableRenderRequestBody":false,"settingEncodeUrl":true,"settingRebuildPath":true,"settingFollowRedirects":"global","_type":"request"},{"_id":"req_e909e0cc58524b54a6be95e05dd3be66","parentId":"fld_159e7a7b20a04c37a3b5143bba516c5e","modified":1728079727531,"created":1728079213346,"url":"http://127.0.0.1:8000/api/user/1","name":"GetOne","description":"","method":"GET","body":{},"parameters":[],"headers":[{"name":"User-Agent","value":"insomnia/10.0.0"}],"authentication":{},"metaSortKey":-1728079703273,"isPrivate":false,"pathParameters":[],"settingStoreCookies":true,"settingSendCookies":true,"settingDisableRenderRequestBody":false,"settingEncodeUrl":true,"settingRebuildPath":true,"settingFollowRedirects":"global","_type":"request"},{"_id":"req_5861e292641f43a3b93a7fae97703e00","parentId":"fld_159e7a7b20a04c37a3b5143bba516c5e","modified":1728079722650,"created":1728079272995,"url":"http://localhost:8000/api/user/1","name":"Delete","description":"","method":"DELETE","body":{},"parameters":[],"headers":[{"name":"User-Agent","value":"insomnia/10.0.0"}],"authentication":{},"metaSortKey":-1728079703223,"isPrivate":false,"pathParameters":[],"settingStoreCookies":true,"settingSendCookies":true,"settingDisableRenderRequestBody":false,"settingEncodeUrl":true,"settingRebuildPath":true,"settingFollowRedirects":"global","_type":"request"},{"_id":"req_af546009c89947258bcf5851aa3ca619","parentId":"fld_159e7a7b20a04c37a3b5143bba516c5e","modified":1728080075384,"created":1728079734764,"url":"http://127.0.0.1:8000/api/user/3","name":"Update","description":"","method":"PATCH","body":{"mimeType":"application/json","text":"{\n\t\"first_name\": \"Alexander\"\n}"},"parameters":[],"headers":[{"name":"Content-Type","value":"application/json","id":"pair_cb358fd5be044c25826e84a66188463f"},{"name":"User-Agent","value":"insomnia/10.0.0","id":"pair_5fd06ab4dc194df6a9f28f2ce4319d4a"},{"id":"pair_d81e9f4208ee4e1faba51b161fdcbce6","name":"Accept","value":"application/json","description":"","disabled":false,"type":"text","multiline":false}],"authentication":{},"metaSortKey":-1728079703235.5,"isPrivate":false,"pathParameters":[],"settingStoreCookies":true,"settingSendCookies":true,"settingDisableRenderRequestBody":false,"settingEncodeUrl":true,"settingRebuildPath":true,"settingFollowRedirects":"global","_type":"request"},{"_id":"req_a3b4309ee93248468af0d404fb46402a","parentId":"fld_0517631b555843a495f990e93a07a964","modified":1728082311528,"created":1728081625644,"url":"http://127.0.0.1:8000/api/companies","name":"GetAll","description":"","method":"GET","body":{},"parameters":[],"headers":[{"name":"User-Agent","value":"insomnia/10.0.0","id":"pair_178e9fad770445f48b2fe57bb4af620a"},{"id":"pair_af60514b8aa24c328e62513f70b38ba8","name":"Accept","value":"application/json","description":"","disabled":false}],"authentication":{},"metaSortKey":-1728079703323,"isPrivate":false,"pathParameters":[],"settingStoreCookies":true,"settingSendCookies":true,"settingDisableRenderRequestBody":false,"settingEncodeUrl":true,"settingRebuildPath":true,"settingFollowRedirects":"global","_type":"request"},{"_id":"req_d2a66bb4b7ff4df1b51b38598d5f87a2","parentId":"fld_0517631b555843a495f990e93a07a964","modified":1728082545248,"created":1728081625644,"url":"http://127.0.0.1:8000/api/company/create","name":"Create","description":"","method":"POST","body":{"mimeType":"application/json","text":"{\n\t\"name\": \"{% faker 'randomCompanyName' %}\",\n\t\"description\": \"{% faker 'randomLoremParagraph' %}\"\n}"},"parameters":[],"headers":[{"name":"Content-Type","value":"application/json","id":"pair_cb358fd5be044c25826e84a66188463f"},{"name":"User-Agent","value":"insomnia/10.0.0","id":"pair_5fd06ab4dc194df6a9f28f2ce4319d4a"},{"id":"pair_d81e9f4208ee4e1faba51b161fdcbce6","name":"Accept","value":"application/json","description":"","disabled":false,"type":"text","multiline":false}],"authentication":{},"metaSortKey":-1728079703248,"isPrivate":false,"pathParameters":[],"settingStoreCookies":true,"settingSendCookies":true,"settingDisableRenderRequestBody":false,"settingEncodeUrl":true,"settingRebuildPath":true,"settingFollowRedirects":"global","_type":"request"},{"_id":"req_0f7d1ec01bf54decb831f20461569bc3","parentId":"fld_0517631b555843a495f990e93a07a964","modified":1728083020827,"created":1728081625645,"url":"http://127.0.0.1:8000/api/company/12","name":"GetOne","description":"","method":"GET","body":{},"parameters":[],"headers":[{"name":"User-Agent","value":"insomnia/10.0.0","id":"pair_3919af1f2fb84c2e82582113afc1e8cd"},{"id":"pair_9ca6a45c0c3849f59cb7e9aa3ebc221c","name":"Accept","value":"application/json","description":"","disabled":false}],"authentication":{},"metaSortKey":-1728079703273,"isPrivate":false,"pathParameters":[],"settingStoreCookies":true,"settingSendCookies":true,"settingDisableRenderRequestBody":false,"settingEncodeUrl":true,"settingRebuildPath":true,"settingFollowRedirects":"global","_type":"request"},{"_id":"req_e6d3d78f78d94d138a4f860eb7035c29","parentId":"fld_0517631b555843a495f990e93a07a964","modified":1728083523184,"created":1728081625645,"url":"http://localhost:8000/api/company/2","name":"Delete","description":"","method":"DELETE","body":{},"parameters":[],"headers":[{"name":"User-Agent","value":"insomnia/10.0.0","id":"pair_43c9a3c227404af58ff57caf6b5a419e"},{"id":"pair_bdcfda05581647f78d713cc61436188c","name":"Accept","value":"application/json","description":"","disabled":false}],"authentication":{},"metaSortKey":-1728079703223,"isPrivate":false,"pathParameters":[],"settingStoreCookies":true,"settingSendCookies":true,"settingDisableRenderRequestBody":false,"settingEncodeUrl":true,"settingRebuildPath":true,"settingFollowRedirects":"global","_type":"request"},{"_id":"req_f801af7582f9476abb35385f5b7ab311","parentId":"fld_0517631b555843a495f990e93a07a964","modified":1728083417275,"created":1728081625646,"url":"http://127.0.0.1:8000/api/company/3","name":"Update","description":"","method":"PATCH","body":{"mimeType":"application/json","text":"{\n\t\"name\": \"Alexander&CO\"\n}"},"parameters":[],"headers":[{"name":"Content-Type","value":"application/json","id":"pair_cb358fd5be044c25826e84a66188463f"},{"name":"User-Agent","value":"insomnia/10.0.0","id":"pair_5fd06ab4dc194df6a9f28f2ce4319d4a"},{"id":"pair_d81e9f4208ee4e1faba51b161fdcbce6","name":"Accept","value":"application/json","description":"","disabled":false,"type":"text","multiline":false}],"authentication":{},"metaSortKey":-1728079703235.5,"isPrivate":false,"pathParameters":[],"settingStoreCookies":true,"settingSendCookies":true,"settingDisableRenderRequestBody":false,"settingEncodeUrl":true,"settingRebuildPath":true,"settingFollowRedirects":"global","_type":"request"},{"_id":"req_73e58524b2d04cc28b16179f80b00d12","parentId":"fld_d3edc7d12ec14ac1984f9d3ba80ba134","modified":1728082863636,"created":1728082858174,"url":"http://127.0.0.1:8000/api/comments","name":"GetAll","description":"","method":"GET","body":{},"parameters":[],"headers":[{"name":"User-Agent","value":"insomnia/10.0.0","id":"pair_178e9fad770445f48b2fe57bb4af620a"},{"id":"pair_af60514b8aa24c328e62513f70b38ba8","name":"Accept","value":"application/json","description":"","disabled":false}],"authentication":{},"metaSortKey":-1728079703323,"isPrivate":false,"pathParameters":[],"settingStoreCookies":true,"settingSendCookies":true,"settingDisableRenderRequestBody":false,"settingEncodeUrl":true,"settingRebuildPath":true,"settingFollowRedirects":"global","_type":"request"},{"_id":"req_00100d00506a4b60817f99df7f78748d","parentId":"fld_d3edc7d12ec14ac1984f9d3ba80ba134","modified":1728086061632,"created":1728082858175,"url":"http://127.0.0.1:8000/api/comment/create","name":"Create","description":"","method":"POST","body":{"mimeType":"application/json","text":"{\n\t\"user_id\": 1,\n\t\"company_id\": 4,\n\t\"content\": \"{% faker 'randomLoremParagraph' %}\",\n\t\"rating\": 6\n}"},"parameters":[],"headers":[{"name":"Content-Type","value":"application/json","id":"pair_cb358fd5be044c25826e84a66188463f"},{"name":"User-Agent","value":"insomnia/10.0.0","id":"pair_5fd06ab4dc194df6a9f28f2ce4319d4a"},{"id":"pair_d81e9f4208ee4e1faba51b161fdcbce6","name":"Accept","value":"application/json","description":"","disabled":false,"type":"text","multiline":false}],"authentication":{},"metaSortKey":-1728079703248,"isPrivate":false,"pathParameters":[],"settingStoreCookies":true,"settingSendCookies":true,"settingDisableRenderRequestBody":false,"settingEncodeUrl":true,"settingRebuildPath":true,"settingFollowRedirects":"global","_type":"request"},{"_id":"req_e1c36c4472c94319ac5aa63aaf07f184","parentId":"fld_d3edc7d12ec14ac1984f9d3ba80ba134","modified":1728082867179,"created":1728082858175,"url":"http://127.0.0.1:8000/api/comment/1","name":"GetOne","description":"","method":"GET","body":{},"parameters":[],"headers":[{"name":"User-Agent","value":"insomnia/10.0.0","id":"pair_3919af1f2fb84c2e82582113afc1e8cd"},{"id":"pair_9ca6a45c0c3849f59cb7e9aa3ebc221c","name":"Accept","value":"application/json","description":"","disabled":false}],"authentication":{},"metaSortKey":-1728079703273,"isPrivate":false,"pathParameters":[],"settingStoreCookies":true,"settingSendCookies":true,"settingDisableRenderRequestBody":false,"settingEncodeUrl":true,"settingRebuildPath":true,"settingFollowRedirects":"global","_type":"request"},{"_id":"req_367e4580b4494af8a2933cb276f6d05e","parentId":"fld_d3edc7d12ec14ac1984f9d3ba80ba134","modified":1728085109253,"created":1728082858176,"url":"http://localhost:8000/api/comment/3","name":"Delete","description":"","method":"DELETE","body":{},"parameters":[],"headers":[{"name":"User-Agent","value":"insomnia/10.0.0","id":"pair_43c9a3c227404af58ff57caf6b5a419e"},{"id":"pair_bdcfda05581647f78d713cc61436188c","name":"Accept","value":"application/json","description":"","disabled":false}],"authentication":{},"metaSortKey":-1728079703223,"isPrivate":false,"pathParameters":[],"settingStoreCookies":true,"settingSendCookies":true,"settingDisableRenderRequestBody":false,"settingEncodeUrl":true,"settingRebuildPath":true,"settingFollowRedirects":"global","_type":"request"},{"_id":"req_cada89ec61ed42c78f8eb2561b173431","parentId":"fld_d3edc7d12ec14ac1984f9d3ba80ba134","modified":1728084812935,"created":1728082858176,"url":"http://127.0.0.1:8000/api/comment/1","name":"Update","description":"","method":"PATCH","body":{"mimeType":"application/json","text":"{\n\t\"content\": \"{% faker 'randomLoremParagraph' %}\"\n}"},"parameters":[],"headers":[{"name":"Content-Type","value":"application/json","id":"pair_cb358fd5be044c25826e84a66188463f"},{"name":"User-Agent","value":"insomnia/10.0.0","id":"pair_5fd06ab4dc194df6a9f28f2ce4319d4a"},{"id":"pair_d81e9f4208ee4e1faba51b161fdcbce6","name":"Accept","value":"application/json","description":"","disabled":false,"type":"text","multiline":false}],"authentication":{},"metaSortKey":-1728079703235.5,"isPrivate":false,"pathParameters":[],"settingStoreCookies":true,"settingSendCookies":true,"settingDisableRenderRequestBody":false,"settingEncodeUrl":true,"settingRebuildPath":true,"settingFollowRedirects":"global","_type":"request"},{"_id":"req_ea822d314acc431c8af1676c8017514c","parentId":"fld_0517631b555843a495f990e93a07a964","modified":1728088111216,"created":1728085318798,"url":"http://localhost:8000/api/company/2/comments/","name":"GetComments","description":"","method":"GET","body":{},"parameters":[],"headers":[{"name":"User-Agent","value":"insomnia/10.0.0","id":"pair_e890c56d8f5f4374958b0b98d5d0e929"},{"id":"pair_8c0d15dad5694a0c84df36f5fc8b8eff","name":"Accept","value":"application/json","description":"","disabled":false}],"authentication":{},"metaSortKey":-1728085318798,"isPrivate":false,"pathParameters":[],"settingStoreCookies":true,"settingSendCookies":true,"settingDisableRenderRequestBody":false,"settingEncodeUrl":true,"settingRebuildPath":true,"settingFollowRedirects":"global","_type":"request"},{"_id":"req_3fe4327c068c42b2b91a392af74e112c","parentId":"fld_0517631b555843a495f990e93a07a964","modified":1728088120095,"created":1728086362071,"url":"http://localhost:8000/api/company/2/rating/","name":"GetRating","description":"","method":"GET","body":{},"parameters":[],"headers":[{"name":"User-Agent","value":"insomnia/10.0.0","id":"pair_e890c56d8f5f4374958b0b98d5d0e929"},{"id":"pair_8c0d15dad5694a0c84df36f5fc8b8eff","name":"Accept","value":"application/json","description":"","disabled":false}],"authentication":{},"metaSortKey":-1728082511060.5,"isPrivate":false,"pathParameters":[],"settingStoreCookies":true,"settingSendCookies":true,"settingDisableRenderRequestBody":false,"settingEncodeUrl":true,"settingRebuildPath":true,"settingFollowRedirects":"global","_type":"request"},{"_id":"req_26be93fa00294237a9773ecee7f53d0d","parentId":"fld_0517631b555843a495f990e93a07a964","modified":1728086536600,"created":1728086516176,"url":"http://localhost:8000/api/companies/top10","name":"GetTop10","description":"","method":"GET","body":{},"parameters":[],"headers":[{"name":"User-Agent","value":"insomnia/10.0.0","id":"pair_e890c56d8f5f4374958b0b98d5d0e929"},{"id":"pair_8c0d15dad5694a0c84df36f5fc8b8eff","name":"Accept","value":"application/json","description":"","disabled":false}],"authentication":{},"metaSortKey":-1728081107191.75,"isPrivate":false,"pathParameters":[],"settingStoreCookies":true,"settingSendCookies":true,"settingDisableRenderRequestBody":false,"settingEncodeUrl":true,"settingRebuildPath":true,"settingFollowRedirects":"global","_type":"request"},{"_id":"fld_159e7a7b20a04c37a3b5143bba516c5e","parentId":"wrk_scratchpad","modified":1728079668073,"created":1728079668073,"name":"USER","description":"","environment":{},"environmentPropertyOrder":null,"metaSortKey":-1728079668073,"_type":"request_group"},{"_id":"fld_0517631b555843a495f990e93a07a964","parentId":"wrk_scratchpad","modified":1728081628698,"created":1728081625643,"name":"COMPANY","description":"","environment":{},"environmentPropertyOrder":null,"metaSortKey":-1728079668023,"_type":"request_group"},{"_id":"fld_d3edc7d12ec14ac1984f9d3ba80ba134","parentId":"wrk_scratchpad","modified":1728082858174,"created":1728082858174,"name":"COMMENT","description":"","environment":{},"environmentPropertyOrder":null,"metaSortKey":-1728079667973,"_type":"request_group"},{"_id":"env_99d30891da4bdcebc63947a8fc17f076de878684","parentId":"wrk_scratchpad","modified":1728055594456,"created":1728055594456,"name":"Base Environment","data":{},"dataPropertyOrder":null,"color":null,"isPrivate":false,"metaSortKey":1728055594456,"_type":"environment"},{"_id":"jar_99d30891da4bdcebc63947a8fc17f076de878684","parentId":"wrk_scratchpad","modified":1728077513379,"created":1728055594516,"name":"Default Jar","cookies":[{"key":"XSRF-TOKEN","value":"eyJpdiI6IjF2U3BUekhiYnRzeXZkdVZwQVFNWXc9PSIsInZhbHVlIjoiZDl6dTBHQ3R5Q0ZlMXd3WXlSVDJQem9tYVJLVjNLTk1mV2VXUE42S21IMmt1R0pJYkl0d3VtTEp2S2FVMDROR0txb003aWNaMlRkL1l3S3Vra3l1NVlaOG9CMlJFdWRjeDk0aFdVeHR1ZkF0TzVmU1RVeUh2MlpITVhjRnFwVWIiLCJtYWMiOiIzNzUyMDg4MDExNTI1MzA2MTRjYmIwNjgwMjg5ZGY1MTJmZGFjNTVhMjdhMjM2Nzc2YWQ4ZGMyZDVhNDkwMzY3IiwidGFnIjoiIn0%3D","expires":"2024-10-04T23:31:53.000Z","maxAge":7200,"domain":"127.0.0.1","path":"/","hostOnly":true,"creation":"2024-10-04T15:29:49.710Z","lastAccessed":"2024-10-04T21:31:53.379Z","sameSite":"lax","id":"c3a27e9a-8eed-41a2-b9a1-f1fb71959d27"},{"key":"laravel_session","value":"eyJpdiI6ImkvOEFDVXkvb2ZLOFZ5NTQ3ZTFGWEE9PSIsInZhbHVlIjoiSFQvOUV3Skl0L3QvYWJzOFVqb1pDMjR6V09CVzRabUpUQVRZb2FaVDNkZzdncW9ROTZMVXJJNHhoN2pUV1VLMnY4TE53bkxzamdLckc1cVFEUGI4eU5ZbThTRkk5N2xoSnV2NXh3eTJSTU9JVjVmcytpRUpDbVIxbVAvc3pNMlUiLCJtYWMiOiI1NDkyY2JhYzdkZWM5Mzc4ZDkwYzI5YjMzYTFkM2RjNmQ2MjNkMjk1ZTk1MzhiY2JiNDAwNzhkNzVlNDc4MWEzIiwidGFnIjoiIn0%3D","expires":"2024-10-04T23:31:53.000Z","maxAge":7200,"domain":"127.0.0.1","path":"/","httpOnly":true,"hostOnly":true,"creation":"2024-10-04T15:29:49.710Z","lastAccessed":"2024-10-04T21:31:53.379Z","sameSite":"lax","id":"f11b014f-c1f4-4b55-8045-946256187947"}],"_type":"cookie_jar"}]}